firestore_model/__init__.py
firestore_model-0.0.5.dist-info/LICENSE
firestore_model-0.0.5.dist-info/METADATA
firestore_model-0.0.5.dist-info/WHEEL
firestore_model-0.0.5.dist-info/top_level.txt
firestore_model-0.0.5.dist-info/RECORD
