Metadata-Version: 2.1
Name: firestore-model
Version: 0.0.5
Summary: A wrapper for creating model classes using Google's Cloud Firestore schemaless database
Home-page: https://gitlab.com/futureprojects/firestore-model
Author: Scibeam
Author-email: jeremy@scibeam.co
License: UNKNOWN
Platform: UNKNOWN
Classifier: Programming Language :: Python :: 3.7
Classifier: License :: OSI Approved :: GNU General Public License v3 or later (GPLv3+)
Classifier: Operating System :: OS Independent
